portmanpy/__init__.py
portmanpy/portfolio.py
portmanpy-0.0.0.dist-info/METADATA
portmanpy-0.0.0.dist-info/WHEEL
portmanpy-0.0.0.dist-info/top_level.txt
portmanpy-0.0.0.dist-info/RECORD
