Metadata-Version: 2.1
Name: portmanpy
Version: 0.0.0
Summary: Portfolio Management for Jupyter
Home-page: https://github.com/genarionogueira/portmanpy
Author: Genario Nogueira
Author-email: genarionogueira2@gmail.com
License: BSD 2-clause
Platform: UNKNOWN
Classifier: Development Status :: 1 - Planning
Classifier: License :: OSI Approved :: BSD License
Classifier: Programming Language :: Python :: 3
Requires-Dist: pandas
